{
  "model_present": true,
  "pad_from_model": true,
  "model_confidence": 0.4533743789197087,
  "pad_from_extractor": false,
  "extractor_severity_label": 1,
  "conclusion": {
    "PAD_present": false,
    "severity_label": 1,
    "severity_text": "Mild"
  },
  "pred_raw": {
    "pad_detected": true,
    "severity": "Mild",
    "proba": [
      0.1949739766991751,
      0.4533743789197087,
      0.22919514717331807,
      0.12245649720779807
    ],
    "label": 1
  },
  "parsed_snapshot": {
    "Patient ID": "B-2025-1102",
    "Patient Name": "Ramesh Gupta",
    "Age": "46",
    "Sex": "Male",
    "Limb": "Arterial Study",
    "ABI": "0.88",
    "Common Femoral Artery PSV": 95.6,
    "Common Femoral Artery Waveform": "Triphasic",
    "Common Femoral Artery Remarks": null,
    "Profundus Femoris PSV": 82.4,
    "Profundus Femoris Waveform": "Triphasic",
    "Profundus Femoris Remarks": null,
    "Proximal SFA PSV": null,
    "Proximal SFA Waveform": null,
    "Proximal SFA Remarks": null,
    "Mid SFA PSV": 87.0,
    "Mid SFA Waveform": "Triphasic",
    "Mid SFA Remarks": null,
    "Distal SFA PSV": 80.5,
    "Distal SFA Waveform": "Triphasic",
    "Distal SFA Remarks": null,
    "Popliteal Artery PSV": 89.7,
    "Popliteal Artery Waveform": "Triphasic",
    "Popliteal Artery Remarks": null,
    "Peroneal / Posterior Tibial Artery PSV": 67.1,
    "Peroneal / Posterior Tibial Artery Waveform": "Triphasic",
    "Peroneal / Posterior Tibial Artery Remarks": null,
    "Anterior Tibial Artery PSV": 70.3,
    "Anterior Tibial Artery Waveform": "Triphasic",
    "Anterior Tibial Artery Remarks": null,
    "waveform_monophasic_count": 0,
    "waveform_biphasic_count": 0,
    "waveform_triphasic_count": 13,
    "Absent_Flow": false,
    "mean_PSV": 81.8,
    "label": 1,
    "Patient Name alt": "Ramesh Gupta",
    "_age_sex_confidence": 3,
    "label_adjusted": 1,
    "_flags_missing": {
      "Age": false,
      "ABI": false,
      "waveform_triphasic_count": false,
      "waveform_monophasic_count": false,
      "age_sex_confidence_low": false
    },
    "_ocr_snippet_near_ABI": "litude and contour for distal vessel. Ankle—Brachial Index (ABI) ABI: 0.88 (Left) Impression 1. Ankle-Brachial Index mildly reduced (ABI 0.88) on the left. 2. Triphasic waveforms a"
  },
  "decision_notes": [
    "model_yes_extractor_no_but_model_mild_lowconf -> used_extractor",
    "abi_override_has_pad (ABI=0.88 <= 0.9)"
  ],
  "abi_numeric": 0.88,
  "abi_has_pad_threshold": 0.9,
  "abi_override_enabled": true,
  "abi_suggests_has_pad": true,
  "abi_non_compressible": false
}